huaweicloudsdkims/__init__.py
huaweicloudsdkims/v2/__init__.py
huaweicloudsdkims/v2/ims_async_client.py
huaweicloudsdkims/v2/ims_client.py
huaweicloudsdkims/v2/model/__init__.py
huaweicloudsdkims/v2/model/add_image_tag_request.py
huaweicloudsdkims/v2/model/add_image_tag_request_body.py
huaweicloudsdkims/v2/model/add_image_tag_response.py
huaweicloudsdkims/v2/model/add_or_update_tags_request_body.py
huaweicloudsdkims/v2/model/additional_properties.py
huaweicloudsdkims/v2/model/batch_add_members_request.py
huaweicloudsdkims/v2/model/batch_add_members_request_body.py
huaweicloudsdkims/v2/model/batch_add_members_response.py
huaweicloudsdkims/v2/model/batch_add_or_delete_tags_request.py
huaweicloudsdkims/v2/model/batch_add_or_delete_tags_request_body.py
huaweicloudsdkims/v2/model/batch_add_or_delete_tags_response.py
huaweicloudsdkims/v2/model/batch_delete_members_request.py
huaweicloudsdkims/v2/model/batch_delete_members_response.py
huaweicloudsdkims/v2/model/batch_delete_tags_request.py
huaweicloudsdkims/v2/model/batch_delete_tags_request_body.py
huaweicloudsdkims/v2/model/batch_delete_tags_response.py
huaweicloudsdkims/v2/model/batch_update_members_request.py
huaweicloudsdkims/v2/model/batch_update_members_request_body.py
huaweicloudsdkims/v2/model/batch_update_members_response.py
huaweicloudsdkims/v2/model/copy_image_cross_region_request.py
huaweicloudsdkims/v2/model/copy_image_cross_region_request_body.py
huaweicloudsdkims/v2/model/copy_image_cross_region_response.py
huaweicloudsdkims/v2/model/copy_image_in_region_in_safe_mode_request.py
huaweicloudsdkims/v2/model/copy_image_in_region_in_safe_mode_response.py
huaweicloudsdkims/v2/model/copy_image_in_region_request.py
huaweicloudsdkims/v2/model/copy_image_in_region_request_body.py
huaweicloudsdkims/v2/model/copy_image_in_region_response.py
huaweicloudsdkims/v2/model/create_data_image.py
huaweicloudsdkims/v2/model/create_data_image_in_safe_mode_request.py
huaweicloudsdkims-3.1.184.dist-info/METADATA
huaweicloudsdkims-3.1.184.dist-info/WHEEL
huaweicloudsdkims-3.1.184.dist-info/licenses/LICENSE
huaweicloudsdkims-3.1.184.dist-info/RECORD
